LICENSE
README.md
bgpneigetpdb/__init__.py
bgpneigetpdb/cli.py
bgpneigetpdb-1.1.4.dist-info/LICENSE
bgpneigetpdb-1.1.4.dist-info/METADATA
bgpneigetpdb-1.1.4.dist-info/WHEEL
bgpneigetpdb-1.1.4.dist-info/entry_points.txt
bgpneigetpdb-1.1.4.dist-info/RECORD
